pyhcrypt/__init__.py
pyhcrypt/__main__.py
pyhcrypt/crypt.py
pyhcrypt-0.0.5.dist-info/LICENSE
pyhcrypt-0.0.5.dist-info/METADATA
pyhcrypt-0.0.5.dist-info/WHEEL
pyhcrypt-0.0.5.dist-info/entry_points.txt
pyhcrypt-0.0.5.dist-info/top_level.txt
pyhcrypt-0.0.5.dist-info/zip-safe
pyhcrypt-0.0.5.dist-info/RECORD
