Metadata-Version: 2.1
Name: pyhcrypt
Version: 0.0.5
Summary: A simple and secure password-based encryption & decryption algorithm based on hash functions, implemented solely based on python.
Home-page: https://github.com/hfxunlp/pyhcrypt
Author: Hongfei Xu
Author-email: hfxunlp@foxmail.com
Maintainer: Hongfei Xu
Maintainer-email: hfxunlp@foxmail.com
License: GNU General Public License v3 (GPLv3)
Keywords: encryption,decryption,hash
Classifier: License :: OSI Approved :: GNU General Public License v3 (GPLv3)
Classifier: Programming Language :: Python
Classifier: Programming Language :: Python :: 3
Classifier: Topic :: Software Development :: Libraries :: Python Modules
Classifier: Topic :: Security :: Cryptography
Classifier: Topic :: Utilities
Requires-Python: >=3.6
License-File: LICENSE
